pyckaxe/__init__.py
pyckaxe/__main__.py
pyckaxe/cli/__init__.py
pyckaxe/cli/cli.py
pyckaxe/cli/utils.py
pyckaxe/lib/__init__.py
pyckaxe/lib/block.py
pyckaxe/lib/block_map.py
pyckaxe/lib/block_state.py
pyckaxe/lib/breadcrumb.py
pyckaxe/lib/command/__init__.py
pyckaxe/lib/command/command.py
pyckaxe/lib/command/command_argument.py
pyckaxe/lib/command/command_literal.py
pyckaxe/lib/command/command_node.py
pyckaxe/lib/command/debug_command.py
pyckaxe/lib/command/raw_command.py
pyckaxe/lib/coordinate.py
pyckaxe/lib/json_serializable.py
pyckaxe/lib/nbt.py
pyckaxe/lib/nbt_serializable.py
pyckaxe/lib/pack/__init__.py
pyckaxe/lib/pack/abc/__init__.py
pyckaxe/lib/pack/abc/resolution_context.py
pyckaxe/lib/pack/abc/resource.py
pyckaxe/lib/pack/abc/resource_deserializer.py
pyckaxe/lib/pack/abc/resource_location_resolver.py
pyckaxe/lib/pack/abc/resource_resolver.py
pyckaxe/lib/pack/abc/resource_scanner.py
pyckaxe/lib/pack/abc/resource_serializer.py
pyckaxe/lib/pack/abc/resource_transformer.py
pyckaxe/lib/pack/common_resource_location_resolver.py
pyckaxe/lib/pack/common_resource_resolver.py
pyckaxe/lib/pack/common_resource_scanner.py
pyckaxe/lib/pack/namespace.py
pyckaxe/lib/pack/pack_context.py
pyckaxe/lib/pack/pack_meta.py
pyckaxe/lib/pack/physical_namespace.py
pyckaxe/lib/pack/physical_pack.py
pyckaxe/lib/pack/physical_registry_location.py
pyckaxe/lib/pack/physical_resource_location.py
pyckaxe/lib/pack/registry_location.py
pyckaxe/lib/pack/resource_cache.py
pyckaxe/lib/pack/resource_dumper/__init__.py
pyckaxe/lib/pack/resource_dumper/abc/__init__.py
pyckaxe/lib/pack/resource_dumper/abc/resource_dumper.py
pyckaxe/lib/pack/resource_dumper/common_resource_dumper.py
pyckaxe/lib/pack/resource_dumper/errors.py
pyckaxe/lib/pack/resource_dumper/json_resource_dumper.py
pyckaxe/lib/pack/resource_dumper/nbt_resource_dumper.py
pyckaxe/lib/pack/resource_dumper/text_resource_dumper.py
pyckaxe/lib/pack/resource_dumper_set.py
pyckaxe/lib/pack/resource_loader/__init__.py
pyckaxe-0.2.0.dist-info/LICENSE.txt
pyckaxe-0.2.0.dist-info/WHEEL
pyckaxe-0.2.0.dist-info/METADATA
pyckaxe-0.2.0.dist-info/RECORD
