Metadata-Version: 2.1
Name: pyckaxe
Version: 0.2.0
Summary: An expressive Minecraft utility library revolving around data manipulation and generation.
Home-page: https://github.com/Arcensoth/pyckaxe
License: MIT
Keywords: minecraft,commands,generators,datapacks
Author: Arcensoth
Author-email: arcensoth@gmail.com
Requires-Python: >=3.8,<4.0
Classifier: License :: OSI Approved :: MIT License
Classifier: Programming Language :: Python :: 3
Classifier: Programming Language :: Python :: 3.8
Classifier: Programming Language :: Python :: 3.9
Provides-Extra: colors
Provides-Extra: yaml
Requires-Dist: click (>=7.1.2,<8.0.0)
Requires-Dist: colorama (>=0.4.3,<0.5.0); extra == "colors"
Requires-Dist: colorlog (>=4.2.1,<5.0.0); extra == "colors"
Requires-Dist: nbtlib (>=1.12.0,<2.0.0)
Requires-Dist: pyyaml (>=5.3.1,<6.0.0); extra == "yaml"
Project-URL: Repository, https://github.com/Arcensoth/pyckaxe
